README.md
setup.py
TagStats.egg-info/PKG-INFO
TagStats.egg-info/SOURCES.txt
TagStats.egg-info/dependency_links.txt
TagStats.egg-info/top_level.txt
tagstats/__init__.py
tagstats/tagstats.py