Metadata-Version: 1.2
Name: TagStats
Version: 0.1.1
Summary: Statistics for each tag's set of key phrases
Home-page: https://github.com/chuanconggao/TagStats
Author: Chuancong Gao
Author-email: chuancong@gmail.com
License: MIT
Download-URL: https://github.com/chuanconggao/TagStats/tarball/0.1.1
Keywords: data structure,sentiment analysis
Platform: UNKNOWN
Classifier: Operating System :: OS Independent
Classifier: Programming Language :: Python
Classifier: Programming Language :: Python :: 3
Requires-Python: >= 3
